system_monitor_mcp/__init__.py
system_monitor_mcp/__main__.py
system_monitor_mcp/collectors.py
system_monitor_mcp/server.py
system_monitor_mcp/utils.py
system_monitor_mcp-1.1.4.dist-info/LICENSE
system_monitor_mcp-1.1.4.dist-info/METADATA
system_monitor_mcp-1.1.4.dist-info/WHEEL
system_monitor_mcp-1.1.4.dist-info/entry_points.txt
system_monitor_mcp-1.1.4.dist-info/top_level.txt
system_monitor_mcp-1.1.4.dist-info/RECORD
