Metadata-Version: 2.1
Name: system-monitor-mcp
Version: 1.1.4
Summary: System Monitor MCP Server - 系统监控MCP服务器
Author-email: Undoom <kaikaihuhu666@163.com>
License: MIT
Project-URL: Homepage, https://github.com/undoom/system-monitor-mcp
Project-URL: Repository, https://github.com/undoom/system-monitor-mcp
Project-URL: Issues, https://github.com/undoom/system-monitor-mcp/issues
Keywords: mcp,system,monitor,server
Classifier: Development Status :: 4 - Beta
Classifier: Programming Language :: Python :: 3
Classifier: Programming Language :: Python :: 3.8
Classifier: Programming Language :: Python :: 3.9
Classifier: Programming Language :: Python :: 3.10
Classifier: Programming Language :: Python :: 3.11
Classifier: Programming Language :: Python :: 3.12
Classifier: Operating System :: OS Independent
License-File: LICENSE
Requires-Dist: mcp>=1.0.0
Requires-Dist: psutil>=5.9.0
Requires-Dist: pydantic>=2.0.0
